Deriverative_Valuation/__init__.py
Deriverative_Valuation/constant_short_rate.py
Deriverative_Valuation/derivatives_portfolio.py
Deriverative_Valuation/derivatives_position.py
Deriverative_Valuation/fetch_option_data.py
Deriverative_Valuation/geometric_brownian_motion.py
Deriverative_Valuation/get_year_deltas.py
Deriverative_Valuation/jump_diffusion.py
Deriverative_Valuation/market_environment.py
Deriverative_Valuation/plot_option_stats.py
Deriverative_Valuation/simulation_class.py
Deriverative_Valuation/sn_random_numbers.py
Deriverative_Valuation/square_root_diffusion.py
Deriverative_Valuation/valuation_class.py
Deriverative_Valuation/valuation_mcs_american.py
Deriverative_Valuation/valuation_mcs_european.py
deriverative_valuation_5917487-0.1.1.dist-info/METADATA
deriverative_valuation_5917487-0.1.1.dist-info/WHEEL
deriverative_valuation_5917487-0.1.1.dist-info/top_level.txt
deriverative_valuation_5917487-0.1.1.dist-info/RECORD
