Metadata-Version: 2.2
Name: deriverative_valuation_5917487
Version: 0.1.1
Summary: see read me on git
Author-email: plato <spamemail2093411@gmail.com>
Classifier: Programming Language :: Python :: 3
Requires-Python: >=3.11.2
